MANIFEST.in
README.md
setup.py
yufou/__init__.py
yufou/radar.py
yufou.egg-info/PKG-INFO
yufou.egg-info/SOURCES.txt
yufou.egg-info/dependency_links.txt
yufou.egg-info/top_level.txt
yufou/data/__init__.py
yufou/data/radar.json
yufou/data/radar.py